FIR.v
module FIR #(parameter width = 16 ,  NUM_TAPS=4) ( 
	input  wire 		                             arst_n,
	input  wire 		                                clk,
    input  wire  signed    [width-1:0]                   Xn,
    output reg   signed    [width-1:0]                   Yn_reg
	
);

//internal registers 
reg signed  [width-1:0] delayed_reg [NUM_TAPS-1:0] ;
wire signed [width-1:0] Yn; 
integer i,d;

always @(posedge clk or negedge arst_n) begin 
	if(~arst_n) begin

			 for (i = 0; i < NUM_TAPS; i=i+1) begin
                 delayed_reg [i] <=0;
             end
			         Yn_reg      <=0;
		
	end else begin
	     	     for (d= NUM_TAPS-1; d >0 ; d=d-1) begin     //x(n-1) = x(n)
                     delayed_reg [d] <= delayed_reg [d-1];
                        end
                      delayed_reg[0] <= Xn;
                       Yn_reg        <= Yn ;                            //output registering
	end      
end

//output assigned with arithematic shift having H=[1 0.5 0.25 0.125]
assign Yn = (Xn + (delayed_reg[1]>>>1) + (delayed_reg[2]>>>2) + (delayed_reg[3]>>>3) ) >>>2  ;

endmodule

FIR_tb.v
`timescale 1ns/1ps
module FIR_tb  #(parameter width = 16, stimulus_num =10,NUM_TAPS=4) ();
	reg		                             arst_n_TB;
	reg		                                clk_TB;
    reg   signed   [width-1:0]               Xn_TB;
    wire  signed   [width-1:0]               Yn_TB;
  // reg  signed   [width-1:0]               Yn_TB;

reg signed [width-1:0] input_stimulus  [0:stimulus_num-1] ;
reg signed [width-1:0] expected_output [0:stimulus_num-1] ;

integer i;

//Initial 
initial
 begin

// System Functions
 $dumpfile("FIR_DUMP.vcd") ;       
 $dumpvars;

//initialization
initialize() ;

//read input txt 
$readmemh("Weighting_filter_input.txt",input_stimulus) ;

//read output txt 
$readmemh("Weighting_filter_output.txt",expected_output) ;

//Reset the design
reset();

// Run test cases
    for (i = 0; i < stimulus_num; i = i + 1) begin
      Xn_TB = input_stimulus[i];
       repeat(NUM_TAPS-1)@(negedge clk_TB);
      if(Yn_TB != expected_output[i])

      	$display("Test %d Failed @time %0t", i ,$time);
      else
      	$display("Test %d Passed @time %0t", i ,$time);
     end

  repeat(1000)@(negedge clk_TB) $stop ;

end 




////////////////////////////////////////////////////////
/////////////////////// TASKS //////////////////////////
////////////////////////////////////////////////////////

/////////////// Signals Initialization //////////////////

task initialize ;
 begin
  clk_TB    = 1'b0 ; 
  i         = 1'b0 ;

 end
endtask

///////////////////////// RESET /////////////////////////

task reset ;
 begin
   arst_n_TB = 1'b1  ;             // rst is deactivated
  @(negedge clk_TB);
   arst_n_TB = 1'b0  ;            // rst is activated
  @(negedge clk_TB);
   arst_n_TB = 1'b1  ;  
 end
endtask

////////////////////////////////////////////////////////
////////////////// Clock Generator  ////////////////////
////////////////////////////////////////////////////////

always #5 clk_TB = ~clk_TB ;


////////////////////////////////////////////////////////
/////////////////// DUT Instantation ///////////////////
////////////////////////////////////////////////////////
FIR DUT(
  .clk     (clk_TB),
  .arst_n(arst_n_TB),
  .Xn       (Xn_TB),
  .Yn_reg      (Yn_TB)
);
endmodule

FIR_DUMP.vcd
$date
	Sun Sep  3 02:12:57 2023
$end
$version
	QuestaSim Version 2021.1
$end
$timescale
	1ps
$end

$scope module FIR_tb $end
$var parameter 32 ! width $end
$var parameter 32 " stimulus_num $end
$var parameter 32 # NUM_TAPS $end
$var reg 1 $ arst_n_TB $end
$var reg 1 % clk_TB $end
$var reg 16 & Xn_TB [15:0] $end
$var wire 1 ' Yn_TB [15] $end
$var wire 1 ( Yn_TB [14] $end
$var wire 1 ) Yn_TB [13] $end
$var wire 1 * Yn_TB [12] $end
$var wire 1 + Yn_TB [11] $end
$var wire 1 , Yn_TB [10] $end
$var wire 1 - Yn_TB [9] $end
$var wire 1 . Yn_TB [8] $end
$var wire 1 / Yn_TB [7] $end
$var wire 1 0 Yn_TB [6] $end
$var wire 1 1 Yn_TB [5] $end
$var wire 1 2 Yn_TB [4] $end
$var wire 1 3 Yn_TB [3] $end
$var wire 1 4 Yn_TB [2] $end
$var wire 1 5 Yn_TB [1] $end
$var wire 1 6 Yn_TB [0] $end
$var integer 32 7 i $end

$scope task initialize $end
$upscope $end

$scope task reset $end
$upscope $end

$scope module DUT $end
$var parameter 32 8 width $end
$var parameter 32 9 NUM_TAPS $end
$var wire 1 : arst_n $end
$var wire 1 ; clk $end
$var wire 1 < Xn [15] $end
$var wire 1 = Xn [14] $end
$var wire 1 > Xn [13] $end
$var wire 1 ? Xn [12] $end
$var wire 1 @ Xn [11] $end
$var wire 1 A Xn [10] $end
$var wire 1 B Xn [9] $end
$var wire 1 C Xn [8] $end
$var wire 1 D Xn [7] $end
$var wire 1 E Xn [6] $end
$var wire 1 F Xn [5] $end
$var wire 1 G Xn [4] $end
$var wire 1 H Xn [3] $end
$var wire 1 I Xn [2] $end
$var wire 1 J Xn [1] $end
$var wire 1 K Xn [0] $end
$var reg 16 L Yn_reg [15:0] $end
$var wire 1 M Yn [15] $end
$var wire 1 N Yn [14] $end
$var wire 1 O Yn [13] $end
$var wire 1 P Yn [12] $end
$var wire 1 Q Yn [11] $end
$var wire 1 R Yn [10] $end
$var wire 1 S Yn [9] $end
$var wire 1 T Yn [8] $end
$var wire 1 U Yn [7] $end
$var wire 1 V Yn [6] $end
$var wire 1 W Yn [5] $end
$var wire 1 X Yn [4] $end
$var wire 1 Y Yn [3] $end
$var wire 1 Z Yn [2] $end
$var wire 1 [ Yn [1] $end
$var wire 1 \ Yn [0] $end
$var integer 32 ] i $end
$var integer 32 ^ d $end
$upscope $end
$upscope $end
$enddefinitions $end
#0
$dumpvars
1$
0%
bx &
bx L
b10000 !
b1010 "
b100 #
b10000 8
b100 9
b0 7
bx ]
bx ^
x6
x5
x4
x3
x2
x1
x0
x/
x.
x-
x,
x+
x*
x)
x(
x'
x\
x[
xZ
xY
xX
xW
xV
xU
xT
xS
xR
xQ
xP
xO
0N
0M
xK
xJ
xI
xH
xG
xF
xE
xD
xC
xB
xA
x@
x?
x>
x=
x<
0;
1:
$end
#5000
1%
1;
b11 ^
b10 ^
b1 ^
b0 ^
b0xxxxxxxxxxxxxx L
0(
0'
#10000
0%
0;
0$
0:
b0 ]
b1 ]
b10 ]
b11 ]
b100 ]
b0 L
06
05
04
03
02
01
00
0/
0.
0-
0,
0+
0*
0)
#15000
1%
1;
b0 ]
b1 ]
b10 ]
b11 ]
b100 ]
#20000
0%
0;
1$
b1101101110 &
0K
1J
1I
1H
0G
1F
1E
0D
1C
1B
0A
0@
0?
0>
0=
0<
1\
1[
0Z
1Y
1X
0W
1V
1U
0T
0S
0R
0Q
0P
0O
1:
#25000
1%
1;
b11 ^
b10 ^
b1 ^
b0 ^
b11011011 L
16
15
13
12
10
1/
#30000
0%
0;
#35000
1%
1;
b11 ^
b10 ^
b1 ^
b0 ^
0[
0X
0U
1T
#40000
0%
0;
#45000
1%
1;
b11 ^
b10 ^
b1 ^
b0 ^
b101001001 L
05
02
0/
1.
0\
0Y
0V
1U
#50000
0%
0;
b1 7
b101001001 &
1K
0J
0I
0F
0B
1[
1Z
1X
1W
1V
0T
#55000
1%
1;
b11 ^
b10 ^
b1 ^
b0 ^
b11110110 L
06
15
14
03
12
11
1/
0.
0Z
0W
0V
0U
1T
#60000
0%
0;
#65000
1%
1;
b11 ^
b10 ^
b1 ^
b0 ^
b100010010 L
04
01
00
0/
1.
1\
0[
1Z
1Y
0X
1V
1U
0T
#70000
0%
0;
#75000
1%
1;
b11 ^
b10 ^
b1 ^
b0 ^
b11001101 L
16
05
14
13
02
10
1/
0.
1[
0Z
1W
0V
#80000
0%
0;
b10 7
b1111110110000000 &
0K
0H
0E
1D
1A
1@
1?
1>
1=
1<
0\
0[
1X
1T
1S
1R
1Q
1P
1O
#85000
1%
1;
b11 ^
b10 ^
b1 ^
b0 ^
b11111110111000 L
06
04
12
11
00
1.
1-
1,
1+
1*
1)
1\
1[
1Z
0Y
0X
#90000
0%
0;
#95000
1%
1;
b11 ^
b10 ^
b1 ^
b0 ^
b11111110100111 L
16
15
14
03
02
0\
1Y
0U
0O
#100000
0%
0;
#105000
1%
1;
b11 ^
b10 ^
b1 ^
b0 ^
b1111100101110 L
06
13
0/
0)
0Z
0Y
1X
1V
1U
0T
0P
1O
#110000
0%
0;
b11 7
b1111110110111011 &
1K
1J
1H
1G
1F
1\
0[
0X
0W
0V
0U
1T
#115000
1%
1;
b11 ^
b10 ^
b1 ^
b0 ^
b10111100000001 L
16
05
04
03
01
0*
1)
0\
1[
1W
1V
1U
0T
0Q
1P
#120000
0%
0;
#125000
1%
1;
b11 ^
b10 ^
b1 ^
b0 ^
b11011011100010 L
06
15
11
10
1/
0.
0+
1*
1Y
#130000
0%
0;
#135000
1%
1;
b11 ^
b10 ^
b1 ^
b0 ^
b11011011101010 L
13
1\
0[
1Z
#140000
0%
0;
b100 7
b1111110111101000 &
0K
0J
0G
1E
0\
0Z
1X
#145000
1%
1;
b11 ^
b10 ^
b1 ^
b0 ^
b11011011111000 L
05
12
1[
#150000
0%
0;
#155000
1%
1;
b11 ^
b10 ^
b1 ^
b0 ^
b11011011111010 L
15
0[
0Y
0X
0W
0V
0U
1T
#160000
0%
0;
#165000
1%
1;
b11 ^
b10 ^
b1 ^
b0 ^
b11011100000000 L
05
03
02
01
00
0/
1.
1\
1[
#170000
0%
0;
b101 7
b1111111011011010 &
1J
1G
0F
0C
1B
1Z
1Y
1X
1W
#175000
1%
1;
b11 ^
b10 ^
b1 ^
b0 ^
b11011100111111 L
16
15
14
13
12
11
0[
0Z
0Y
0X
0W
1V
#180000
0%
0;
#185000
1%
1;
b11 ^
b10 ^
b1 ^
b0 ^
b11011101000001 L
05
04
03
02
01
10
1[
1Z
1Y
1X
#190000
0%
0;
#195000
1%
1;
b11 ^
b10 ^
b1 ^
b0 ^
b11011101011111 L
15
14
13
12
0\
0X
1W
#200000
0%
0;
b110 7
b110011101 &
1K
0J
1I
0E
1C
0B
0A
0@
0?
0>
0=
0<
1\
1X
0W
0V
0T
0S
0R
1Q
#205000
1%
1;
b11 ^
b10 ^
b1 ^
b0 ^
b11100000011111 L
00
0.
0-
0,
1+
0\
0Y
0X
1W
#210000
0%
0;
#215000
1%
1;
b11 ^
b10 ^
b1 ^
b0 ^
b11100000100110 L
06
03
02
11
1\
1Y
1X
1V
0O
#220000
0%
0;
#225000
1%
1;
b11 ^
b10 ^
b1 ^
b0 ^
b1100001111111 L
16
13
12
10
0)
0Z
0X
0V
1U
0P
#230000
0%
0;
b111 7
b1111101110101101 &
0G
1F
1B
1@
1?
1>
1=
1<
1Z
0U
1T
1S
1R
0Q
#235000
1%
1;
b11 ^
b10 ^
b1 ^
b0 ^
b11100101111 L
02
00
1.
1-
1,
0+
0*
0[
0Y
0W
1V
1Q
1P
1O
#240000
0%
0;
#245000
1%
1;
b11 ^
b10 ^
b1 ^
b0 ^
b11111101000101 L
05
03
01
10
1+
1*
1)
1[
0V
1U
0T
0O
#250000
0%
0;
#255000
1%
1;
b11 ^
b10 ^
b1 ^
b0 ^
b1111010000111 L
15
00
1/
0.
0)
0\
0[
0Z
1Y
1W
0U
0P
1O
#260000
0%
0;
b1000 7
b1111100110101011 &
1J
0I
0B
1\
1[
1Z
0Y
1U
1T
0S
#265000
1%
1;
b11 ^
b10 ^
b1 ^
b0 ^
b10110110100111 L
11
1.
0-
0*
1)
0\
0[
0Z
1Y
1X
1V
0U
0Q
1P
#270000
0%
0;
#275000
1%
1;
b11 ^
b10 ^
b1 ^
b0 ^
b11010101111000 L
06
05
04
13
12
10
0/
0+
1*
0V
#280000
0%
0;
#285000
1%
1;
b11 ^
b10 ^
b1 ^
b0 ^
b11010100111000 L
00
1\
1[
1Z
0Y
0W
#290000
0%
0;
b1001 7
b100010001 &
0J
0H
1G
0F
0D
0@
0?
0>
0=
0<
0[
0Z
1W
1V
1U
0T
1S
#295000
1%
1;
b11 ^
b10 ^
b1 ^
b0 ^
b11011011110001 L
16
03
10
1/
0.
1-
0X
#300000
0%
0;
#305000
1%
1;
b11 ^
b10 ^
b1 ^
b0 ^
b11011011100001 L
02
0\
1[
1Z
1Y
0W
1T
0O
#310000
0%
0;
#315000
1%
1;
b11 ^
b10 ^
b1 ^
b0 ^
b1011111001110 L
06
15
14
13
01
1.
0)
0[
0Y
0U
0T
0S
0R
1Q
0P
#320000
0%
0;
b1010 7
#325000
1%
1;
b11 ^
b10 ^
b1 ^
b0 ^
b100001000100 L
05
03
0/
0.
0-
0,
1+
0*
1\
1[
1Y
1X
1W
0Q
